{
  "美国": {
    "first_seen": "2025-11-17T09:30:03+00:00",
    "sources": [],
    "original_forms": [
      "US farmers",
      "Сполучених Штатів Америки",
      "美國",
      "Штатам",
      "Senate",
      "États-Unis",
      "美国",
      "美利坚合众国",
      "the United States",
      "米国",
      "Washington",
      "United States",
      "米"
    ]
  },
  "特朗普": {
    "first_seen": "2025-12-08T22:29:27+00:00",
    "sources": [],
    "original_forms": [
      "Donald Trump",
      "President Trump",
      "特朗普",
      "Trump"
    ]
  },
  "委内瑞拉": {
    "first_seen": "2025-12-08T22:44:27+00:00",
    "sources": [],
    "original_forms": [
      "Venezuelan"
    ]
  },
  "波克罗夫斯克": {
    "first_seen": "2025-12-08T22:48:00+00:00",
    "sources": [],
    "original_forms": [
      "Покровськом"
    ]
  },
  "米尔诺格勒": {
    "first_seen": "2025-12-08T21:03:59+00:00",
    "sources": [],
    "original_forms": [
      "Мирноградом",
      "Мирнограду"
    ]
  },
  "AC米兰": {
    "first_seen": "2025-12-08T22:36:00+00:00",
    "sources": [],
    "original_forms": [
      "AC Milan"
    ]
  },
  "克里斯蒂安·普利西奇": {
    "first_seen": "2025-12-08T22:18:19+00:00",
    "sources": [],
    "original_forms": [
      "Christian Pulišić",
      "克里斯蒂安·普利西奇",
      "Christian Pulisic"
    ]
  },
  "意大利足球甲级联赛": {
    "first_seen": "2025-12-08T22:36:00+00:00",
    "sources": [],
    "original_forms": [
      "意大利足球甲级联赛",
      "Championnat d’Italie",
      "Serie A"
    ]
  },
  "Nvidia": {
    "first_seen": "2025-12-08T22:42:00+00:00",
    "sources": [],
    "original_forms": [
      "Nvidia"
    ]
  },
  "ComfyUI": {
    "first_seen": "2025-12-08T22:42:00+00:00",
    "sources": [],
    "original_forms": [
      "ComfyUI"
    ]
  },
  "FLUX.2": {
    "first_seen": "2025-12-08T22:42:00+00:00",
    "sources": [],
    "original_forms": [
      "FLUX.2"
    ]
  },
  "Blender": {
    "first_seen": "2025-12-08T22:42:00+00:00",
    "sources": [],
    "original_forms": [
      "Blender"
    ]
  },
  "Topaz Video AI": {
    "first_seen": "2025-12-08T22:42:00+00:00",
    "sources": [],
    "original_forms": [
      "Topaz Video AI"
    ]
  },
  "Topaz Photo AI": {
    "first_seen": "2025-12-08T22:42:00+00:00",
    "sources": [],
    "original_forms": [
      "Topaz Photo AI"
    ]
  },
  "美国最高法院": {
    "first_seen": "2025-12-08T22:47:00+00:00",
    "sources": [],
    "original_forms": [
      "Supreme Court"
    ]
  },
  "斯劳特": {
    "first_seen": "2025-12-08T22:47:00+00:00",
    "sources": [],
    "original_forms": [
      "Slaughter"
    ]
  },
  "Luigi Mangione": {
    "first_seen": "2025-12-08T22:15:00+00:00",
    "sources": [],
    "original_forms": [
      "Luigi Mangione"
    ]
  },
  "麦当劳": {
    "first_seen": "2025-12-08T22:15:00+00:00",
    "sources": [],
    "original_forms": [
      "McDonald's",
      "McDonald’s"
    ]
  },
  "宾夕法尼亚州": {
    "first_seen": "2025-12-08T22:15:00+00:00",
    "sources": [],
    "original_forms": [
      "Pennsylvania"
    ]
  },
  "唐纳德·特朗普": {
    "first_seen": "2025-12-08T18:33:30+00:00",
    "sources": [],
    "original_forms": [
      "Donald Trump",
      "Дональд Трамп"
    ]
  },
  "阿尔图纳警察局": {
    "first_seen": "2025-12-08T22:34:59+00:00",
    "sources": [],
    "original_forms": [
      "Altoona police"
    ]
  },
  "弗拉门戈": {
    "first_seen": "2025-12-08T22:00:00+00:00",
    "sources": [],
    "original_forms": [
      "Flamengo",
      "弗拉门戈"
    ]
  },
  "Luiz Eduardo Baptista": {
    "first_seen": "2025-12-08T22:32:19+00:00",
    "sources": [],
    "original_forms": [
      "Luiz Eduardo Baptista"
    ]
  },
  "曼彻斯特联足球俱乐部": {
    "first_seen": "2025-12-08T19:18:45+00:00",
    "sources": [],
    "original_forms": [
      "曼彻斯特联足球俱乐部",
      "曼联",
      "Manchester United"
    ]
  },
  "布鲁诺·费尔南德斯": {
    "first_seen": "2025-12-08T22:30:30+00:00",
    "sources": [],
    "original_forms": [
      "Bruno Fernandes"
    ]
  },
  "莫利纽球场": {
    "first_seen": "2025-12-08T22:30:30+00:00",
    "sources": [],
    "original_forms": [
      "Molineux"
    ]
  },
  "Paulinho da Força": {
    "first_seen": "2025-12-08T22:33:00+00:00",
    "sources": [],
    "original_forms": [
      "Paulinho da Força"
    ]
  },
  "CartaCapital": {
    "first_seen": "2025-12-08T22:33:00+00:00",
    "sources": [],
    "original_forms": [
      "CartaCapital"
    ]
  },
  "projeto de lei que pode reduzir as penas de condenados por envolvimento no 8 de Janeiro": {
    "first_seen": "2025-12-08T22:33:00+00:00",
    "sources": [],
    "original_forms": [
      "projeto de lei que pode reduzir as penas de condenados por envolvimento no 8 de Janeiro"
    ]
  },
  "参议院": {
    "first_seen": "2025-12-08T22:34:17+00:00",
    "sources": [],
    "original_forms": [
      "John Thune"
    ]
  },
  "约翰·图恩": {
    "first_seen": "2025-12-08T22:34:17+00:00",
    "sources": [],
    "original_forms": [
      "GOP"
    ]
  },
  "共和党": {
    "first_seen": "2025-12-08T22:34:17+00:00",
    "sources": [],
    "original_forms": [
      "Democrats",
      "共和"
    ]
  },
  "Pedro Gómez": {
    "first_seen": "2025-12-08T22:26:17+00:00",
    "sources": [],
    "original_forms": [
      "Pedro Gómez"
    ]
  },
  "Prefectura Naval Argentina": {
    "first_seen": "2025-12-08T22:26:17+00:00",
    "sources": [],
    "original_forms": [
      "Prefectura Naval Argentina"
    ]
  },
  "María Venegas": {
    "first_seen": "2025-12-08T22:26:17+00:00",
    "sources": [],
    "original_forms": [
      "María Venegas"
    ]
  },
  "Carlos Kikuchi": {
    "first_seen": "2025-12-08T22:28:40+00:00",
    "sources": [],
    "original_forms": [
      "Carlos Kikuchi"
    ]
  },
  "Verónica Magar": {
    "first_seen": "2025-12-08T22:28:40+00:00",
    "sources": [],
    "original_forms": [
      "Verónica Magar"
    ]
  },
  "布宜诺斯艾利斯省参议院": {
    "first_seen": "2025-12-08T22:28:40+00:00",
    "sources": [],
    "original_forms": [
      "Senado bonaerense"
    ]
  },
  "国际货币基金组织": {
    "first_seen": "2025-12-08T22:29:00+00:00",
    "sources": [],
    "original_forms": [
      "Fondo Monetario Internacional (FMI)"
    ]
  },
  "F-16": {
    "first_seen": "2025-12-08T22:29:00+00:00",
    "sources": [],
    "original_forms": [
      "F-16"
    ]
  },
  "Estudiantes": {
    "first_seen": "2025-12-08T22:26:14+00:00",
    "sources": [],
    "original_forms": [
      "Estudiantes"
    ]
  },
  "Gimnasia": {
    "first_seen": "2025-12-08T22:26:14+00:00",
    "sources": [],
    "original_forms": [
      "Gimnasia"
    ]
  },
  "Eduardo Domínguez": {
    "first_seen": "2025-12-08T22:26:14+00:00",
    "sources": [],
    "original_forms": [
      "Eduardo Domínguez"
    ]
  },
  "巴西": {
    "first_seen": "2025-12-08T22:26:23+00:00",
    "sources": [],
    "original_forms": [
      "Brasil"
    ]
  },
  "交通部": {
    "first_seen": "2025-11-14T03:45:40+00:00",
    "sources": [],
    "original_forms": [
      "交通部",
      "Ministério dos Transportes"
    ]
  },
  "Renan Filho": {
    "first_seen": "2025-12-08T22:26:23+00:00",
    "sources": [],
    "original_forms": [
      "Renan Filho"
    ]
  },
  "巴西民主运动党": {
    "first_seen": "2025-12-08T22:26:23+00:00",
    "sources": [],
    "original_forms": [
      "MDB"
    ]
  },
  "阿根廷政府": {
    "first_seen": "2025-12-08T22:06:00+00:00",
    "sources": [],
    "original_forms": [
      "阿根廷政府",
      "Gobierno",
      "Argentina",
      "阿根廷",
      "el Gobierno"
    ]
  },
  "Bruno Fernandes": {
    "first_seen": "2025-12-08T22:23:22+00:00",
    "sources": [],
    "original_forms": [
      "Bruno Fernandes"
    ]
  },
  "英国政府": {
    "first_seen": "2025-12-08T22:30:00+00:00",
    "sources": [],
    "original_forms": [
      "the government",
      "英国政府",
      "英国"
    ]
  },
  "大不列颠铁路公司": {
    "first_seen": "2025-12-08T22:30:00+00:00",
    "sources": [],
    "original_forms": [
      "Great British Railways"
    ]
  },
  "Xreal Project Aura": {
    "first_seen": "2025-12-08T22:18:00+00:00",
    "sources": [],
    "original_forms": [
      "Xreal Project Aura"
    ]
  },
  "PC Connect": {
    "first_seen": "2025-12-08T22:18:00+00:00",
    "sources": [],
    "original_forms": [
      "PC Connect"
    ]
  },
  "美国军队": {
    "first_seen": "2025-12-08T22:19:19+00:00",
    "sources": [],
    "original_forms": [
      "the Pentagon",
      "美国军队",
      "美国国防部",
      "the United States military"
    ]
  },
  "亚历山大·奥西波夫": {
    "first_seen": "2025-12-08T22:14:32+00:00",
    "sources": [],
    "original_forms": [
      "Александром Осиповым"
    ]
  },
  "后贝加尔边疆区": {
    "first_seen": "2025-12-08T22:14:32+00:00",
    "sources": [],
    "original_forms": [
      "Забайкалья"
    ]
  },
  "阿根廷参议院": {
    "first_seen": "2025-12-08T22:09:51+00:00",
    "sources": [],
    "original_forms": [
      "Senado"
    ]
  },
  "全国第十二届残疾人运动会": {
    "first_seen": "2025-12-08T22:17:00+00:00",
    "sources": [],
    "original_forms": [
      "全国第十二届残疾人运动会"
    ]
  },
  "第九届特殊奥林匹克运动会": {
    "first_seen": "2025-12-08T22:17:00+00:00",
    "sources": [],
    "original_forms": [
      "第九届特殊奥林匹克运动会"
    ]
  },
  "粤港澳": {
    "first_seen": "2025-12-08T22:17:00+00:00",
    "sources": [],
    "original_forms": [
      "粤港澳"
    ]
  },
  "全国34个代表团": {
    "first_seen": "2025-12-08T22:17:00+00:00",
    "sources": [],
    "original_forms": [
      "全国34个代表团"
    ]
  },
  "福建队": {
    "first_seen": "2025-12-08T22:17:00+00:00",
    "sources": [],
    "original_forms": [
      "福建队"
    ]
  },
  "河南队": {
    "first_seen": "2025-12-08T22:17:00+00:00",
    "sources": [],
    "original_forms": [
      "河南队"
    ]
  },
  "盲人足球项目": {
    "first_seen": "2025-12-08T22:17:00+00:00",
    "sources": [],
    "original_forms": [
      "盲人足球项目"
    ]
  },
  "新加坡": {
    "first_seen": "2025-12-08T22:15:00+00:00",
    "sources": [],
    "original_forms": [
      "新加坡国家档案馆",
      "Singapore",
      "National Archives of Singapore",
      "新加坡"
    ]
  },
  "马来西亚": {
    "first_seen": "2025-11-21T06:23:51+00:00",
    "sources": [],
    "original_forms": [
      "馬來西亞",
      "马来西亚",
      "Malaysia",
      "青森县",
      "青森県"
    ]
  },
  "吴庆瑞": {
    "first_seen": "2025-12-08T22:15:00+00:00",
    "sources": [],
    "original_forms": [
      "Dr Goh Keng Swee"
    ]
  },
  "Netflix": {
    "first_seen": "2025-12-08T21:32:00+00:00",
    "sources": [],
    "original_forms": [
      "Netflix"
    ]
  },
  "David Ellison": {
    "first_seen": "2025-12-08T21:13:51+00:00",
    "sources": [],
    "original_forms": [
      "David Ellison"
    ]
  },
  "维多利亚·邦亚": {
    "first_seen": "2025-12-08T22:14:19+00:00",
    "sources": [],
    "original_forms": [
      "Виктория Боня"
    ]
  },
  "阿根廷卫生部": {
    "first_seen": "2025-12-08T22:08:00+00:00",
    "sources": [],
    "original_forms": [
      "Ministerio de Salud"
    ]
  },
  "乌拉圭": {
    "first_seen": "2025-12-08T22:08:00+00:00",
    "sources": [],
    "original_forms": [
      "Uruguay"
    ]
  },
  "玻利维亚": {
    "first_seen": "2025-12-08T22:08:00+00:00",
    "sources": [],
    "original_forms": [
      "Bolivia"
    ]
  },
  "CGT": {
    "first_seen": "2025-12-08T22:06:00+00:00",
    "sources": [],
    "original_forms": [
      "CGT"
    ]
  },
  "苹果公司": {
    "first_seen": "2025-12-08T20:30:35+00:00",
    "sources": [],
    "original_forms": [
      "谷歌公司",
      "Google",
      "苹果公司",
      "Apple"
    ]
  },
  "Android": {
    "first_seen": "2025-12-08T22:06:58+00:00",
    "sources": [],
    "original_forms": [
      "Android"
    ]
  },
  "iPhone": {
    "first_seen": "2025-12-08T22:06:58+00:00",
    "sources": [],
    "original_forms": [
      "iPhone"
    ]
  },
  "欧洲": {
    "first_seen": "2025-12-08T14:47:40+00:00",
    "sources": [],
    "original_forms": [
      "l’Europe",
      "欧洲",
      "欧州"
    ]
  },
  "华盛顿": {
    "first_seen": "2025-12-08T22:07:45+00:00",
    "sources": [],
    "original_forms": [
      "Washington"
    ]
  },
  "Matthew Perry": {
    "first_seen": "2025-12-08T22:02:00+00:00",
    "sources": [],
    "original_forms": [
      "Matthew Perry"
    ]
  },
  "CBS News": {
    "first_seen": "2025-12-08T22:02:00+00:00",
    "sources": [],
    "original_forms": [
      "CBS News"
    ]
  },
  "《哪吒2》": {
    "first_seen": "2025-12-08T22:03:00+00:00",
    "sources": [],
    "original_forms": [
      "《哪吒2》"
    ]
  },
  "《疯狂动物城2》": {
    "first_seen": "2025-12-08T22:03:00+00:00",
    "sources": [],
    "original_forms": [
      "《疯狂动物城2》"
    ]
  },
  "中国电影": {
    "first_seen": "2025-12-08T22:03:00+00:00",
    "sources": [],
    "original_forms": [
      "中国电影"
    ]
  },
  "利物浦": {
    "first_seen": "2025-12-08T21:27:00+00:00",
    "sources": [],
    "original_forms": [
      "Liverpool",
      "利物浦"
    ]
  },
  "阿利松": {
    "first_seen": "2025-12-08T22:00:54+00:00",
    "sources": [],
    "original_forms": [
      "Alisson"
    ]
  },
  "阿尔内·斯洛特": {
    "first_seen": "2025-12-08T22:00:54+00:00",
    "sources": [],
    "original_forms": [
      "Max Allegri",
      "Arne Slot",
      "阿尔内·斯洛特",
      "马克斯·阿莱格里"
    ]
  },
  "国际米兰": {
    "first_seen": "2025-12-08T22:00:54+00:00",
    "sources": [],
    "original_forms": [
      "Inter de Milão",
      "Internazionale",
      "Inter Milan"
    ]
  },
  "巴西足球联合会": {
    "first_seen": "2025-12-08T22:00:00+00:00",
    "sources": [],
    "original_forms": [
      "Confederação Brasileira de Futebol"
    ]
  },
  "Caixa Econômica Federal": {
    "first_seen": "2025-12-08T21:57:06+00:00",
    "sources": [],
    "original_forms": [
      "Caixa Econômica"
    ]
  },
  "Quina": {
    "first_seen": "2025-12-08T21:57:06+00:00",
    "sources": [],
    "original_forms": [
      "Quina"
    ]
  },
  "弗拉基米尔·普京": {
    "first_seen": "2025-12-08T16:09:04+00:00",
    "sources": [],
    "original_forms": [
      "Владимир Путин",
      "普京"
    ]
  },
  "Ceará": {
    "first_seen": "2025-12-08T22:00:53+00:00",
    "sources": [],
    "original_forms": [
      "Ceará"
    ]
  },
  "Fortaleza": {
    "first_seen": "2025-12-08T22:00:53+00:00",
    "sources": [],
    "original_forms": [
      "Fortaleza"
    ]
  },
  "Juventude": {
    "first_seen": "2025-12-08T22:00:53+00:00",
    "sources": [],
    "original_forms": [
      "Juventude"
    ]
  },
  "Sport": {
    "first_seen": "2025-12-08T22:00:53+00:00",
    "sources": [],
    "original_forms": [
      "Sport"
    ]
  },
  "Campeonato Brasileiro": {
    "first_seen": "2025-12-08T22:00:53+00:00",
    "sources": [],
    "original_forms": [
      "Brasileirão"
    ]
  },
  "日本气象厅": {
    "first_seen": "2025-12-08T21:22:55+00:00",
    "sources": [],
    "original_forms": [
      "気象庁"
    ]
  },
  "北海道": {
    "first_seen": "2025-12-08T21:22:55+00:00",
    "sources": [],
    "original_forms": [
      "北海道"
    ]
  },
  "岩手县": {
    "first_seen": "2025-12-08T21:39:00+00:00",
    "sources": [],
    "original_forms": [
      "岩手県"
    ]
  },
  "乔·拜登": {
    "first_seen": "2025-12-08T21:44:34+00:00",
    "sources": [],
    "original_forms": [
      "Джо Байден"
    ]
  },
  "乌克兰": {
    "first_seen": "2025-12-08T20:45:00+00:00",
    "sources": [],
    "original_forms": [
      "Україна",
      "Українa",
      "Тернополі",
      "Україні"
    ]
  },
  "白宫": {
    "first_seen": "2025-12-08T21:44:34+00:00",
    "sources": [],
    "original_forms": [
      "Білому домі"
    ]
  },
  "环球小姐组织": {
    "first_seen": "2025-12-08T21:39:21+00:00",
    "sources": [],
    "original_forms": [
      "Miss Universo"
    ]
  },
  "牙买加": {
    "first_seen": "2025-12-08T21:39:21+00:00",
    "sources": [],
    "original_forms": [
      "Jamaica"
    ]
  },
  "Gabrielle Henry": {
    "first_seen": "2025-12-08T21:39:21+00:00",
    "sources": [],
    "original_forms": [
      "Gabrielle Henry"
    ]
  },
  "Montereau-Fault-Yonne": {
    "first_seen": "2025-12-08T21:33:00+00:00",
    "sources": [],
    "original_forms": [
      "Montereau-Fault-Yonne"
    ]
  },
  "Seine-et-Marne": {
    "first_seen": "2025-12-08T21:33:00+00:00",
    "sources": [],
    "original_forms": [
      "Seine-et-Marne"
    ]
  },
  "刚果民主共和国": {
    "first_seen": "2025-12-08T21:35:21+00:00",
    "sources": [],
    "original_forms": [
      "RDC"
    ]
  },
  "齐塞克迪": {
    "first_seen": "2025-12-08T21:35:21+00:00",
    "sources": [],
    "original_forms": [
      "Tshisekedi"
    ]
  },
  "卢旺达": {
    "first_seen": "2025-12-08T21:35:21+00:00",
    "sources": [],
    "original_forms": [
      "Rwanda"
    ]
  },
  "Hariel Lucas Santos de Melo": {
    "first_seen": "2025-12-08T21:28:56+00:00",
    "sources": [],
    "original_forms": [
      "Hariel Lucas Santos de Melo"
    ]
  },
  "Santa Luzia": {
    "first_seen": "2025-12-08T21:28:56+00:00",
    "sources": [],
    "original_forms": [
      "Santa Luzia"
    ]
  },
  "Belo Vale": {
    "first_seen": "2025-12-08T21:28:56+00:00",
    "sources": [],
    "original_forms": [
      "bairro Belo Vale"
    ]
  },
  "Belo Horizonte": {
    "first_seen": "2025-12-08T21:28:56+00:00",
    "sources": [],
    "original_forms": [
      "Região Metropolitana de Belo Horizonte"
    ]
  },
  "Arne Slot": {
    "first_seen": "2025-12-08T21:27:00+00:00",
    "sources": [],
    "original_forms": [
      "Arne Slot"
    ]
  },
  "Ted Sarandos": {
    "first_seen": "2025-12-08T21:32:00+00:00",
    "sources": [],
    "original_forms": [
      "Ted Sarandos"
    ]
  },
  "Paramount": {
    "first_seen": "2025-12-08T21:32:00+00:00",
    "sources": [],
    "original_forms": [
      "Paramount"
    ]
  },
  "东北地方": {
    "first_seen": "2025-12-08T21:22:55+00:00",
    "sources": [],
    "original_forms": [
      "東北地方"
    ]
  },
  "千叶县": {
    "first_seen": "2025-12-08T21:22:55+00:00",
    "sources": [],
    "original_forms": [
      "千葉県"
    ]
  },
  "三陆冲": {
    "first_seen": "2025-12-08T21:22:55+00:00",
    "sources": [],
    "original_forms": [
      "三陸沖"
    ]
  },
  "日本海沟": {
    "first_seen": "2025-12-08T21:22:55+00:00",
    "sources": [],
    "original_forms": [
      "日本海溝"
    ]
  },
  "千岛海沟": {
    "first_seen": "2025-12-08T21:22:55+00:00",
    "sources": [],
    "original_forms": [
      "千島海溝"
    ]
  },
  "巴黎圣日耳曼足球俱乐部": {
    "first_seen": "2025-12-08T21:30:47+00:00",
    "sources": [],
    "original_forms": [
      "PSG"
    ]
  },
  "卢卡斯·谢瓦利耶": {
    "first_seen": "2025-12-08T21:30:47+00:00",
    "sources": [],
    "original_forms": [
      "Lucas Chevalier"
    ]
  },
  "毕尔巴鄂竞技": {
    "first_seen": "2025-12-08T21:30:47+00:00",
    "sources": [],
    "original_forms": [
      "Bilbao"
    ]
  },
  "摩纳哥足球俱乐部": {
    "first_seen": "2025-12-08T21:30:47+00:00",
    "sources": [],
    "original_forms": [
      "AS Monaco"
    ]
  },
  "里尔": {
    "first_seen": "2025-12-08T21:30:47+00:00",
    "sources": [],
    "original_forms": [
      "Rennes",
      "l’AS Monaco",
      "雷恩足球俱乐部",
      "里尔"
    ]
  },
  "法国足球甲级联赛": {
    "first_seen": "2025-12-08T21:30:47+00:00",
    "sources": [],
    "original_forms": [
      "Ligue 1"
    ]
  },
  "Skydance Media": {
    "first_seen": "2025-12-08T21:19:07+00:00",
    "sources": [],
    "original_forms": [
      "Skydance Media",
      "Skydance",
      "Paramount Skydance"
    ]
  },
  "埃里森家族": {
    "first_seen": "2025-12-08T21:19:07+00:00",
    "sources": [],
    "original_forms": [
      "Ellison family"
    ]
  },
  "基辅": {
    "first_seen": "2025-12-08T21:07:54+00:00",
    "sources": [],
    "original_forms": [
      "Києві"
    ]
  },
  "派拉蒙": {
    "first_seen": "2025-12-08T21:13:51+00:00",
    "sources": [],
    "original_forms": [
      "Paramount",
      "派拉蒙环球",
      "派拉蒙"
    ]
  },
  "华纳兄弟探索": {
    "first_seen": "2025-12-08T21:13:51+00:00",
    "sources": [],
    "original_forms": [
      "Warner Bros Discovery",
      "Warner Bros. Discovery",
      "华纳兄弟探索",
      "华纳兄弟探索公司"
    ]
  },
  "David Zaslav": {
    "first_seen": "2025-12-08T21:13:51+00:00",
    "sources": [],
    "original_forms": [
      "David Zaslav"
    ]
  },
  "法国": {
    "first_seen": "2025-12-08T20:18:02+00:00",
    "sources": [],
    "original_forms": [
      "フランス",
      "France",
      "法国"
    ]
  },
  "荷兰": {
    "first_seen": "2025-12-08T21:04:07+00:00",
    "sources": [],
    "original_forms": [
      "阿姆斯特丹泛欧交易所",
      "荷兰",
      "Pays-Bas"
    ]
  },
  "丹麦": {
    "first_seen": "2025-12-08T21:04:07+00:00",
    "sources": [],
    "original_forms": [
      "Danemark"
    ]
  },
  "Matthieu Chedid": {
    "first_seen": "2025-12-08T21:04:05+00:00",
    "sources": [],
    "original_forms": [
      "Matthieu Chedid"
    ]
  },
  "Martin Parr": {
    "first_seen": "2025-12-08T21:04:05+00:00",
    "sources": [],
    "original_forms": [
      "Martin Parr"
    ]
  },
  "土屋太凤": {
    "first_seen": "2025-12-08T21:00:00+00:00",
    "sources": [],
    "original_forms": [
      "土屋太凤",
      "土屋太鳳"
    ]
  },
  "Snow Man": {
    "first_seen": "2025-12-08T21:00:00+00:00",
    "sources": [],
    "original_forms": [
      "Snow Man"
    ]
  },
  "美联储": {
    "first_seen": "2025-12-08T20:32:43+00:00",
    "sources": [],
    "original_forms": [
      "美国联邦储备理事会",
      "美国财政部",
      "米連邦準備理事会（ＦＲＢ）",
      "米連邦公開市場委員会（ＦＯＭＣ）",
      "Federal Reserve",
      "U.S. Treasury",
      "美联储联邦公开市场委员会",
      "美国联邦公开市场委员会",
      "美联储",
      "連邦公開市場委員会（ＦＯＭＣ）"
    ]
  },
  "萨默塞特郡": {
    "first_seen": "2025-12-08T20:42:43+00:00",
    "sources": [],
    "original_forms": [
      "Somerset"
    ]
  },
  "Abu Dhabi Grand Prix": {
    "first_seen": "2025-12-08T20:42:43+00:00",
    "sources": [],
    "original_forms": [
      "Abu Dhabi Grand Prix"
    ]
  },
  "约克": {
    "first_seen": "2025-12-08T20:45:05+00:00",
    "sources": [],
    "original_forms": [
      "York"
    ]
  },
  "佐久間大介": {
    "first_seen": "2025-12-08T21:00:00+00:00",
    "sources": [],
    "original_forms": [
      "佐久间大介",
      "佐久間大介"
    ]
  },
  "内田英治": {
    "first_seen": "2025-12-08T21:00:00+00:00",
    "sources": [],
    "original_forms": [
      "内田英治"
    ]
  },
  "捷尔诺波尔市": {
    "first_seen": "2025-12-08T20:45:00+00:00",
    "sources": [],
    "original_forms": [
      "Тернополю"
    ]
  },
  "捷尔诺波尔州警察局": {
    "first_seen": "2025-12-08T20:45:00+00:00",
    "sources": [],
    "original_forms": [
      "поліції Тернопільської області"
    ]
  },
  "乌克兰第7空中突击军": {
    "first_seen": "2025-12-08T21:03:59+00:00",
    "sources": [],
    "original_forms": [
      "7-й армійський корпус Десантно-штурмових військ"
    ]
  },
  "乌克兰国防军": {
    "first_seen": "2025-12-08T21:03:59+00:00",
    "sources": [],
    "original_forms": [
      "乌克兰国防军",
      "乌克兰武装部队",
      "ЗСУ",
      "Сили оборони"
    ]
  },
  "利西夫卡": {
    "first_seen": "2025-12-08T21:03:59+00:00",
    "sources": [],
    "original_forms": [
      "Лисівки"
    ]
  },
  "苏希亚尔": {
    "first_seen": "2025-12-08T21:03:59+00:00",
    "sources": [],
    "original_forms": [
      "Сухого Яру"
    ]
  },
  "TikTok": {
    "first_seen": "2025-12-08T20:23:00+00:00",
    "sources": [],
    "original_forms": [
      "TikTok"
    ]
  },
  "iPhone 18 Pro": {
    "first_seen": "2025-12-08T20:30:35+00:00",
    "sources": [],
    "original_forms": [
      "iPhone 18 Pro"
    ]
  },
  "Face ID": {
    "first_seen": "2025-12-08T20:30:35+00:00",
    "sources": [],
    "original_forms": [
      "Face ID"
    ]
  },
  "哈茨克维奇": {
    "first_seen": "2025-12-08T20:10:00+00:00",
    "sources": [],
    "original_forms": [
      "Хацкевич"
    ]
  },
  "丹尼斯拉夫·列兹尼科夫": {
    "first_seen": "2025-12-08T20:10:00+00:00",
    "sources": [],
    "original_forms": [
      "Денис Резніков"
    ]
  },
  "波利西亚足球俱乐部": {
    "first_seen": "2025-12-08T20:10:00+00:00",
    "sources": [],
    "original_forms": [
      "Полісся"
    ]
  },
  "鲁赫足球俱乐部": {
    "first_seen": "2025-12-08T20:10:00+00:00",
    "sources": [],
    "original_forms": [
      "Рух"
    ]
  },
  "朝日电视台": {
    "first_seen": "2025-12-08T20:18:39+00:00",
    "sources": [],
    "original_forms": [
      "テレビ朝日"
    ]
  },
  "南原清隆": {
    "first_seen": "2025-12-08T20:18:39+00:00",
    "sources": [],
    "original_forms": [
      "南原清隆"
    ]
  },
  "菊池风磨": {
    "first_seen": "2025-12-08T20:18:39+00:00",
    "sources": [],
    "original_forms": [
      "菊池風磨"
    ]
  },
  "timelesz": {
    "first_seen": "2025-12-08T20:18:39+00:00",
    "sources": [],
    "original_forms": [
      "timelesz"
    ]
  },
  "冯德莱恩": {
    "first_seen": "2025-12-08T19:44:30+00:00",
    "sources": [],
    "original_forms": [
      "Фон дер Ляйен"
    ]
  },
  "中国": {
    "first_seen": "2025-11-11T02:30:04+00:00",
    "sources": [],
    "original_forms": [
      "中华人民共和国",
      "我国",
      "中国",
      "中國",
      "China"
    ]
  },
  "日本": {
    "first_seen": "2025-11-14T03:27:42+00:00",
    "sources": [],
    "original_forms": [
      "東北地方",
      "日本勢",
      "政府",
      "日本",
      "日本东北地方",
      "日本政府"
    ]
  },
  "自衛隊": {
    "first_seen": "2025-12-08T20:18:02+00:00",
    "sources": [],
    "original_forms": [
      "自衛隊"
    ]
  },
  "光明日报": {
    "first_seen": "2025-12-08T19:35:00+00:00",
    "sources": [],
    "original_forms": [
      "光明日报记者 陈晨"
    ]
  },
  "陈晨": {
    "first_seen": "2025-12-08T19:35:00+00:00",
    "sources": [],
    "original_forms": [
      "安胜蓝"
    ]
  },
  "Jonny Evans": {
    "first_seen": "2025-12-08T19:35:35+00:00",
    "sources": [],
    "original_forms": [
      "Jonny Evans"
    ]
  },
  "陈晓": {
    "first_seen": "2025-12-08T20:16:22+00:00",
    "sources": [],
    "original_forms": [
      "陈晓"
    ]
  },
  "成毅": {
    "first_seen": "2025-12-08T20:16:22+00:00",
    "sources": [],
    "original_forms": [
      "成毅"
    ]
  },
  "习近平": {
    "first_seen": "2025-11-14T03:27:42+00:00",
    "sources": [],
    "original_forms": [
      "习近平",
      "Xi Jinping"
    ]
  },
  "李强": {
    "first_seen": "2025-12-08T19:35:00+00:00",
    "sources": [],
    "original_forms": [
      "李强"
    ]
  },
  "蔡奇": {
    "first_seen": "2025-12-08T19:35:00+00:00",
    "sources": [],
    "original_forms": [
      "蔡奇"
    ]
  },
  "丁薛祥": {
    "first_seen": "2025-12-08T19:35:00+00:00",
    "sources": [],
    "original_forms": [
      "丁薛祥"
    ]
  },
  "韩国": {
    "first_seen": "2025-12-08T19:27:08+00:00",
    "sources": [],
    "original_forms": [
      "顿涅茨克州",
      "韓国",
      "Донецької області",
      "Южной Кореи",
      "韩国"
    ]
  },
  "洛杉矶足球俱乐部": {
    "first_seen": "2025-12-08T19:27:08+00:00",
    "sources": [],
    "original_forms": [
      "Лос-Анджелеса"
    ]
  },
  "孙兴慜": {
    "first_seen": "2025-12-08T19:27:08+00:00",
    "sources": [],
    "original_forms": [
      "Сон Хын Мин"
    ]
  },
  "康斯坦丁·沃尔科夫": {
    "first_seen": "2025-12-08T19:25:00+00:00",
    "sources": [],
    "original_forms": [
      "Константин Волков"
    ]
  },
  "亚历山大·切尔内赫": {
    "first_seen": "2025-12-08T19:25:00+00:00",
    "sources": [],
    "original_forms": [
      "Александр Черных"
    ]
  },
  "西伯利亚": {
    "first_seen": "2025-12-08T19:25:00+00:00",
    "sources": [],
    "original_forms": [
      "Сибирь"
    ]
  },
  "Nomos": {
    "first_seen": "2025-12-08T19:00:00+00:00",
    "sources": [],
    "original_forms": [
      "Nomos"
    ]
  },
  "欧洲理事会": {
    "first_seen": "2025-12-08T14:47:40+00:00",
    "sources": [],
    "original_forms": [
      "欧洲理事会"
    ]
  },
  "António Costa": {
    "first_seen": "2025-12-08T14:47:40+00:00",
    "sources": [],
    "original_forms": [
      "António Costa"
    ]
  },
  "水晶宫足球俱乐部": {
    "first_seen": "2025-12-08T19:18:45+00:00",
    "sources": [],
    "original_forms": [
      "Crystal Palace"
    ]
  },
  "雷克瑟姆足球俱乐部": {
    "first_seen": "2025-12-08T19:18:45+00:00",
    "sources": [],
    "original_forms": [
      "雷克瑟姆足球俱乐部",
      "Wrexham",
      "麦克尔斯菲尔德足球俱乐部",
      "Macclesfield"
    ]
  },
  "英格兰足球超级联赛": {
    "first_seen": "2025-12-08T19:18:45+00:00",
    "sources": [],
    "original_forms": [
      "Premier League"
    ]
  },
  "英格兰足球总会": {
    "first_seen": "2025-12-08T19:18:45+00:00",
    "sources": [],
    "original_forms": [
      "FA Cup"
    ]
  },
  "连南瑶族自治县": {
    "first_seen": "2025-12-08T14:10:02+00:00",
    "sources": [],
    "original_forms": [
      "连南瑶族自治县"
    ]
  },
  "唐桥辛二公": {
    "first_seen": "2025-12-08T14:10:02+00:00",
    "sources": [],
    "original_forms": [
      "唐桥辛二公"
    ]
  },
  "安娜莱娜·贝尔伯克": {
    "first_seen": "2025-12-08T16:09:04+00:00",
    "sources": [],
    "original_forms": [
      "德国外长瓦德富尔（Johann Wadephul）"
    ]
  },
  "北京": {
    "first_seen": "2025-12-08T16:09:04+00:00",
    "sources": [],
    "original_forms": [
      "北京",
      "京"
    ]
  },
  "俄罗斯联邦": {
    "first_seen": "2025-12-08T16:09:04+00:00",
    "sources": [],
    "original_forms": [
      "российских активов",
      "rusa",
      "俄罗斯",
      "російського",
      "俄罗斯联邦",
      "России",
      "俄罗斯政府",
      "правительством"
    ]
  },
  "德国驻华大使馆": {
    "first_seen": "2025-12-04T12:50:00+00:00",
    "sources": [],
    "original_forms": [
      "德国驻华大使馆",
      "ドイツ",
      "德意志联邦共和国",
      "德国"
    ]
  },
  "草蜢": {
    "first_seen": "2025-11-23T12:56:52+00:00",
    "sources": [],
    "original_forms": [
      "草蜢"
    ]
  },
  "陈豪": {
    "first_seen": "2025-11-23T12:56:52+00:00",
    "sources": [],
    "original_forms": [
      "陳慧嫻",
      "陈慧娴",
      "陈豪",
      "陳豪",
      "CY陳宗澤",
      "陈宗泽"
    ]
  },
  "唐诗咏": {
    "first_seen": "2025-11-23T12:56:52+00:00",
    "sources": [],
    "original_forms": [
      "唐詩詠"
    ]
  },
  "许靖韵": {
    "first_seen": "2025-11-23T12:56:52+00:00",
    "sources": [],
    "original_forms": [
      "許靖韻"
    ]
  },
  "Niantic": {
    "first_seen": "2025-11-23T09:00:25+00:00",
    "sources": [],
    "original_forms": [
      "Niantic"
    ]
  },
  "Pokémon GO": {
    "first_seen": "2025-11-23T09:00:25+00:00",
    "sources": [],
    "original_forms": [
      "Pokémon GO"
    ]
  },
  "联合国": {
    "first_seen": "2025-12-08T14:53:01+00:00",
    "sources": [],
    "original_forms": [
      "联合国人道主义事务协调厅",
      "联合国人道主义事务协调厅（OCHA）",
      "联合国",
      "国連"
    ]
  },
  "范瑋琪": {
    "first_seen": "2025-11-16T02:37:30+00:00",
    "sources": [],
    "original_forms": [
      "范冰冰",
      "范瑋琪"
    ]
  },
  "杭州": {
    "first_seen": "2025-11-16T02:37:30+00:00",
    "sources": [],
    "original_forms": [
      "杭州"
    ]
  },
  "福岛第一核电站": {
    "first_seen": "2025-11-19T09:35:26+00:00",
    "sources": [],
    "original_forms": [
      "福島第一核電廠"
    ]
  },
  "高市早苗": {
    "first_seen": "2025-11-14T03:27:42+00:00",
    "sources": [],
    "original_forms": [
      "高市早苗"
    ]
  },
  "台湾电影金马奖": {
    "first_seen": "2025-11-21T06:23:51+00:00",
    "sources": [],
    "original_forms": [
      "台湾电影金马奖",
      "金马奖",
      "金馬獎",
      "台灣電影金馬獎"
    ]
  },
  "张吉安": {
    "first_seen": "2025-11-21T06:23:51+00:00",
    "sources": [],
    "original_forms": [
      "張吉安"
    ]
  },
  "中共": {
    "first_seen": "2025-12-01T01:07:00+00:00",
    "sources": [],
    "original_forms": [
      "中共",
      "中共中央",
      "Chinese Communist Party"
    ]
  },
  "台湾": {
    "first_seen": "2025-12-01T01:07:00+00:00",
    "sources": [],
    "original_forms": [
      "台灣",
      "台"
    ]
  },
  "关西地区": {
    "first_seen": "2025-12-01T01:07:00+00:00",
    "sources": [],
    "original_forms": [
      "關西地區"
    ]
  },
  "日本产经新闻": {
    "first_seen": "2025-12-01T01:07:00+00:00",
    "sources": [],
    "original_forms": [
      "日本產經新聞"
    ]
  },
  "大阪观光局": {
    "first_seen": "2025-12-01T01:07:00+00:00",
    "sources": [],
    "original_forms": [
      "大阪觀光局"
    ]
  },
  "经济学人": {
    "first_seen": "2025-11-17T09:30:03+00:00",
    "sources": [],
    "original_forms": [
      "《經濟學人》"
    ]
  },
  "GlobeScan": {
    "first_seen": "2025-11-17T09:30:03+00:00",
    "sources": [],
    "original_forms": [
      "GlobeScan"
    ]
  },
  "暴雪": {
    "first_seen": "2025-11-11T02:30:04+00:00",
    "sources": [],
    "original_forms": [
      "暴雪"
    ]
  },
  "中国国家新闻出版署": {
    "first_seen": "2025-11-11T02:30:04+00:00",
    "sources": [],
    "original_forms": [
      "中国国家新闻出版署"
    ]
  },
  "澳门特别行政区": {
    "first_seen": "2025-11-18T08:17:42+00:00",
    "sources": [],
    "original_forms": [
      "澳門"
    ]
  },
  "岑浩辉": {
    "first_seen": "2025-11-18T08:17:42+00:00",
    "sources": [],
    "original_forms": [
      "岑浩輝"
    ]
  },
  "菲利佩·路易斯": {
    "first_seen": "2025-12-08T22:32:19+00:00",
    "sources": [],
    "original_forms": [
      "Filipe Luís"
    ]
  },
  "狼队": {
    "first_seen": "2025-12-08T22:23:22+00:00",
    "sources": [],
    "original_forms": [
      "狼队",
      "伍尔弗汉普顿流浪者足球俱乐部",
      "Wolves"
    ]
  },
  "穆罕默德·萨拉赫": {
    "first_seen": "2025-12-08T21:27:00+00:00",
    "sources": [],
    "original_forms": [
      "萨拉赫",
      "Mohamed Salah",
      "穆罕默德·萨拉赫",
      "Salah"
    ]
  },
  "兰多·诺里斯": {
    "first_seen": "2025-12-08T20:42:43+00:00",
    "sources": [],
    "original_forms": [
      "Lando Norris"
    ]
  },
  "Lucas Hernandez": {
    "first_seen": "2025-12-08T21:47:00+00:00",
    "sources": [
      {
        "id": "1dd24060388881c7004c431a3332e3ec",
        "name": "Foot01.com",
        "url": "https://www.foot01.com",
        "country": "fr"
      }
    ],
    "original_forms": [
      "Lucas Hernandez"
    ]
  },
  "欧洲足球联盟": {
    "first_seen": "2025-12-08T21:47:00+00:00",
    "sources": [
      {
        "id": "1dd24060388881c7004c431a3332e3ec",
        "name": "Foot01.com",
        "url": "https://www.foot01.com",
        "country": "fr"
      }
    ],
    "original_forms": [
      "C1"
    ]
  },
  "Adrien Rabiot": {
    "first_seen": "2025-12-08T20:55:44+00:00",
    "sources": [
      {
        "id": "89cf2616bd368132eca37d5e3d9f0598",
        "name": "L'Équipe",
        "url": "https://www.lequipe.fr",
        "country": "fr"
      }
    ],
    "original_forms": [
      "Adrien Rabiot"
    ]
  },
  "马尔科·兰杜奇": {
    "first_seen": "2025-12-08T22:38:20+00:00",
    "sources": [
      {
        "id": "8d71923b22fd94776aed4dd1c611fd91",
        "name": "Yardbarker",
        "url": "https://www.yardbarker.com",
        "country": "us"
      }
    ],
    "original_forms": [
      "Marco Landucci"
    ]
  },
  "都灵": {
    "first_seen": "2025-12-08T20:55:44+00:00",
    "sources": [],
    "original_forms": [
      "Torino",
      "都灵足球俱乐部",
      "都灵"
    ]
  },
  "意大利": {
    "first_seen": "2025-12-08T22:13:43+00:00",
    "sources": [
      {
        "id": "f0fc90dfc09bbf76d69b287e66a5d09d",
        "name": "WTOP",
        "url": "https://wtop.com",
        "country": "us"
      }
    ],
    "original_forms": [
      "Italy"
    ]
  },
  "Marko Lazetic": {
    "first_seen": "2025-12-04T19:19:24+00:00",
    "sources": [
      {
        "id": "70f0e86899d38a3c4301bfc5b89b2ff4",
        "name": "Daily Record",
        "url": "https://www.dailyrecord.co.uk",
        "country": "gb"
      }
    ],
    "original_forms": [
      "Marko Lazetic"
    ]
  },
  "Aberdeen": {
    "first_seen": "2025-12-04T19:19:24+00:00",
    "sources": [
      {
        "id": "70f0e86899d38a3c4301bfc5b89b2ff4",
        "name": "Daily Record",
        "url": "https://www.dailyrecord.co.uk",
        "country": "gb"
      }
    ],
    "original_forms": [
      "Aberdeen"
    ]
  },
  "St Mirren": {
    "first_seen": "2025-12-04T19:19:24+00:00",
    "sources": [
      {
        "id": "70f0e86899d38a3c4301bfc5b89b2ff4",
        "name": "Daily Record",
        "url": "https://www.dailyrecord.co.uk",
        "country": "gb"
      }
    ],
    "original_forms": [
      "St Mirren"
    ]
  },
  "拉齐奥": {
    "first_seen": "2025-12-07T23:00:00+00:00",
    "sources": [
      {
        "id": "5c3dbf9ebe394da687e079958be63250",
        "name": "RMC Sport",
        "url": "https://rmcsport.bfmtv.com",
        "country": "fr"
      }
    ],
    "original_forms": [
      "Lazio"
    ]
  },
  "Napoli": {
    "first_seen": "2025-11-30T22:24:32+00:00",
    "sources": [
      {
        "id": "72bbcd9c095a3d51c97cdda7a97dba31",
        "name": "The Straits Times",
        "url": "https://www.straitstimes.com",
        "country": "sg"
      }
    ],
    "original_forms": [
      "Napoli"
    ]
  },
  "AS Roma": {
    "first_seen": "2025-11-30T22:24:32+00:00",
    "sources": [
      {
        "id": "72bbcd9c095a3d51c97cdda7a97dba31",
        "name": "The Straits Times",
        "url": "https://www.straitstimes.com",
        "country": "sg"
      }
    ],
    "original_forms": [
      "AS Roma"
    ]
  },
  "David Neres": {
    "first_seen": "2025-11-30T22:24:32+00:00",
    "sources": [
      {
        "id": "72bbcd9c095a3d51c97cdda7a97dba31",
        "name": "The Straits Times",
        "url": "https://www.straitstimes.com",
        "country": "sg"
      }
    ],
    "original_forms": [
      "David Neres"
    ]
  },
  "Stadio Olimpico": {
    "first_seen": "2025-11-30T22:24:32+00:00",
    "sources": [
      {
        "id": "72bbcd9c095a3d51c97cdda7a97dba31",
        "name": "The Straits Times",
        "url": "https://www.straitstimes.com",
        "country": "sg"
      }
    ],
    "original_forms": [
      "Stadio Olimpico"
    ]
  },
  "纽卡斯尔联队": {
    "first_seen": "2025-12-05T09:30:30+00:00",
    "sources": [
      {
        "id": "3396ad417e0d2903accd5a027a93503e",
        "name": "Evening Chronicle",
        "url": "https://www.chroniclelive.co.uk",
        "country": "gb"
      }
    ],
    "original_forms": [
      "Newcastle United"
    ]
  },
  "桑德罗·托纳利": {
    "first_seen": "2025-12-05T09:30:30+00:00",
    "sources": [
      {
        "id": "3396ad417e0d2903accd5a027a93503e",
        "name": "Evening Chronicle",
        "url": "https://www.chroniclelive.co.uk",
        "country": "gb"
      }
    ],
    "original_forms": [
      "Sandro Tonali"
    ]
  },
  "托特纳姆热刺": {
    "first_seen": "2025-12-05T09:30:30+00:00",
    "sources": [
      {
        "id": "3396ad417e0d2903accd5a027a93503e",
        "name": "Evening Chronicle",
        "url": "https://www.chroniclelive.co.uk",
        "country": "gb"
      }
    ],
    "original_forms": [
      "Tottenham Hotspur"
    ]
  },
  "圣詹姆斯公园球场": {
    "first_seen": "2025-12-05T09:30:30+00:00",
    "sources": [
      {
        "id": "3396ad417e0d2903accd5a027a93503e",
        "name": "Evening Chronicle",
        "url": "https://www.chroniclelive.co.uk",
        "country": "gb"
      }
    ],
    "original_forms": [
      "St James' Park"
    ]
  },
  "伯恩利": {
    "first_seen": "2025-12-05T09:30:30+00:00",
    "sources": [
      {
        "id": "3396ad417e0d2903accd5a027a93503e",
        "name": "Evening Chronicle",
        "url": "https://www.chroniclelive.co.uk",
        "country": "gb"
      }
    ],
    "original_forms": [
      "Burnley"
    ]
  },
  "Mike Maignan": {
    "first_seen": "2025-11-23T22:02:53+00:00",
    "sources": [
      {
        "id": "72bbcd9c095a3d51c97cdda7a97dba31",
        "name": "The Straits Times",
        "url": "https://www.straitstimes.com",
        "country": "sg"
      }
    ],
    "original_forms": [
      "Mike Maignan"
    ]
  },
  "Hakan Calhanoglu": {
    "first_seen": "2025-11-23T22:02:53+00:00",
    "sources": [
      {
        "id": "72bbcd9c095a3d51c97cdda7a97dba31",
        "name": "The Straits Times",
        "url": "https://www.straitstimes.com",
        "country": "sg"
      }
    ],
    "original_forms": [
      "Hakan Calhanoglu"
    ]
  },
  "圣西罗球场": {
    "first_seen": "2025-11-23T22:02:53+00:00",
    "sources": [
      {
        "id": "72bbcd9c095a3d51c97cdda7a97dba31",
        "name": "The Straits Times",
        "url": "https://www.straitstimes.com",
        "country": "sg"
      }
    ],
    "original_forms": [
      "San Siro"
    ]
  },
  "那不勒斯足球俱乐部": {
    "first_seen": "2025-11-30T22:14:44+00:00",
    "sources": [],
    "original_forms": [
      "那不勒斯足球俱乐部",
      "那不勒斯",
      "Napoli"
    ]
  },
  "罗马足球俱乐部": {
    "first_seen": "2025-11-30T22:14:44+00:00",
    "sources": [
      {
        "id": "72bbcd9c095a3d51c97cdda7a97dba31",
        "name": "The Straits Times",
        "url": "https://www.straitstimes.com",
        "country": "sg"
      }
    ],
    "original_forms": [
      "AS Roma"
    ]
  },
  "摩尔线程": {
    "first_seen": "2025-12-09T00:00:00+00:00",
    "sources": [
      {
        "id": "82cf1e5ed5d6b74255ea7c2d29340b4b",
        "name": "21st Century Business Herald ",
        "url": "https://www.21jingji.com",
        "country": "cn"
      }
    ],
    "original_forms": [
      "摩尔线程"
    ]
  },
  "上海证券交易所": {
    "first_seen": "2025-12-09T00:00:00+00:00",
    "sources": [
      {
        "id": "82cf1e5ed5d6b74255ea7c2d29340b4b",
        "name": "21st Century Business Herald ",
        "url": "https://www.21jingji.com",
        "country": "cn"
      }
    ],
    "original_forms": [
      "上交所科创板"
    ]
  },
  "联合利华": {
    "first_seen": "2025-12-09T00:00:00+00:00",
    "sources": [
      {
        "id": "82cf1e5ed5d6b74255ea7c2d29340b4b",
        "name": "21st Century Business Herald ",
        "url": "https://www.21jingji.com",
        "country": "cn"
      }
    ],
    "original_forms": [
      "联合利华"
    ]
  },
  "梦龙": {
    "first_seen": "2025-12-09T00:00:00+00:00",
    "sources": [
      {
        "id": "82cf1e5ed5d6b74255ea7c2d29340b4b",
        "name": "21st Century Business Herald ",
        "url": "https://www.21jingji.com",
        "country": "cn"
      }
    ],
    "original_forms": [
      "梦龙"
    ]
  },
  "伦敦证券交易所": {
    "first_seen": "2025-12-09T00:00:00+00:00",
    "sources": [
      {
        "id": "82cf1e5ed5d6b74255ea7c2d29340b4b",
        "name": "21st Century Business Herald ",
        "url": "https://www.21jingji.com",
        "country": "cn"
      }
    ],
    "original_forms": [
      "伦敦证券交易所"
    ]
  },
  "纽约证券交易所": {
    "first_seen": "2025-12-09T00:00:00+00:00",
    "sources": [
      {
        "id": "82cf1e5ed5d6b74255ea7c2d29340b4b",
        "name": "21st Century Business Herald ",
        "url": "https://www.21jingji.com",
        "country": "cn"
      }
    ],
    "original_forms": [
      "纽约证券交易所"
    ]
  },
  "AgiBot": {
    "first_seen": "2025-12-08T03:30:00+00:00",
    "sources": [
      {
        "id": "4609d947e914f80baf7d9cbbf3958178",
        "name": "ギズモード・ジャパン",
        "url": "https://www.gizmodo.jp",
        "country": "jp"
      }
    ],
    "original_forms": [
      "AgiBot"
    ]
  },
  "A2": {
    "first_seen": "2025-12-08T03:30:00+00:00",
    "sources": [
      {
        "id": "4609d947e914f80baf7d9cbbf3958178",
        "name": "ギズモード・ジャパン",
        "url": "https://www.gizmodo.jp",
        "country": "jp"
      }
    ],
    "original_forms": [
      "A2"
    ]
  },
  "吉尼斯世界纪录": {
    "first_seen": "2025-12-08T03:30:00+00:00",
    "sources": [
      {
        "id": "4609d947e914f80baf7d9cbbf3958178",
        "name": "ギズモード・ジャパン",
        "url": "https://www.gizmodo.jp",
        "country": "jp"
      }
    ],
    "original_forms": [
      "ギネス世界記録"
    ]
  },
  "摩根士丹利": {
    "first_seen": "2025-12-09T00:00:00+00:00",
    "sources": [
      {
        "id": "82cf1e5ed5d6b74255ea7c2d29340b4b",
        "name": "21st Century Business Herald ",
        "url": "https://www.21jingji.com",
        "country": "cn"
      }
    ],
    "original_forms": [
      "Morgan Stanley"
    ]
  },
  "邢自强": {
    "first_seen": "2025-12-09T00:00:00+00:00",
    "sources": [
      {
        "id": "82cf1e5ed5d6b74255ea7c2d29340b4b",
        "name": "21st Century Business Herald ",
        "url": "https://www.21jingji.com",
        "country": "cn"
      }
    ],
    "original_forms": [
      "Xing Ziqiang"
    ]
  },
  "南方财经论坛": {
    "first_seen": "2025-12-09T00:00:00+00:00",
    "sources": [
      {
        "id": "82cf1e5ed5d6b74255ea7c2d29340b4b",
        "name": "21st Century Business Herald ",
        "url": "https://www.21jingji.com",
        "country": "cn"
      }
    ],
    "original_forms": [
      "Nanfang Finance Forum"
    ]
  },
  "东京都": {
    "first_seen": "2025-12-08T03:35:02+00:00",
    "sources": [
      {
        "id": "ec8a18e873d0452c6b532d7a46d9671e",
        "name": "Sankei Shimbun",
        "url": "https://www.sankei.com",
        "country": "jp"
      }
    ],
    "original_forms": [
      "東京都"
    ]
  },
  "缅甸": {
    "first_seen": "2025-12-08T03:35:02+00:00",
    "sources": [
      {
        "id": "ec8a18e873d0452c6b532d7a46d9671e",
        "name": "Sankei Shimbun",
        "url": "https://www.sankei.com",
        "country": "jp"
      }
    ],
    "original_forms": [
      "ミャンマー"
    ]
  },
  "柬埔寨": {
    "first_seen": "2025-12-08T03:35:02+00:00",
    "sources": [
      {
        "id": "ec8a18e873d0452c6b532d7a46d9671e",
        "name": "Sankei Shimbun",
        "url": "https://www.sankei.com",
        "country": "jp"
      }
    ],
    "original_forms": [
      "カンボジア"
    ]
  },
  "白俄罗斯": {
    "first_seen": "2025-12-08T03:35:02+00:00",
    "sources": [
      {
        "id": "ec8a18e873d0452c6b532d7a46d9671e",
        "name": "Sankei Shimbun",
        "url": "https://www.sankei.com",
        "country": "jp"
      }
    ],
    "original_forms": [
      "ベラルーシ"
    ]
  },
  "英国文化教育协会": {
    "first_seen": "2025-12-09T00:00:00+00:00",
    "sources": [
      {
        "id": "82cf1e5ed5d6b74255ea7c2d29340b4b",
        "name": "21st Century Business Herald ",
        "url": "https://www.21jingji.com",
        "country": "cn"
      }
    ],
    "original_forms": [
      "英国文化教育协会"
    ]
  },
  "史蕾": {
    "first_seen": "2025-12-09T00:00:00+00:00",
    "sources": [
      {
        "id": "82cf1e5ed5d6b74255ea7c2d29340b4b",
        "name": "21st Century Business Herald ",
        "url": "https://www.21jingji.com",
        "country": "cn"
      }
    ],
    "original_forms": [
      "史蕾"
    ]
  },
  "郑青亭": {
    "first_seen": "2025-12-09T00:00:00+00:00",
    "sources": [
      {
        "id": "82cf1e5ed5d6b74255ea7c2d29340b4b",
        "name": "21st Century Business Herald ",
        "url": "https://www.21jingji.com",
        "country": "cn"
      }
    ],
    "original_forms": [
      "郑青亭"
    ]
  },
  "倪缤缤": {
    "first_seen": "2025-12-09T00:00:00+00:00",
    "sources": [
      {
        "id": "82cf1e5ed5d6b74255ea7c2d29340b4b",
        "name": "21st Century Business Herald ",
        "url": "https://www.21jingji.com",
        "country": "cn"
      }
    ],
    "original_forms": [
      "倪缤缤"
    ]
  },
  "QS国际学生调查": {
    "first_seen": "2025-12-09T00:00:00+00:00",
    "sources": [
      {
        "id": "82cf1e5ed5d6b74255ea7c2d29340b4b",
        "name": "21st Century Business Herald ",
        "url": "https://www.21jingji.com",
        "country": "cn"
      }
    ],
    "original_forms": [
      "QS International Student Survey"
    ]
  },
  "新启航半导体": {
    "first_seen": "2025-12-09T00:00:00+00:00",
    "sources": [
      {
        "id": "82cf1e5ed5d6b74255ea7c2d29340b4b",
        "name": "21st Century Business Herald ",
        "url": "https://www.21jingji.com",
        "country": "cn"
      }
    ],
    "original_forms": [
      "新启航半导体"
    ]
  },
  "华特气体": {
    "first_seen": "2025-12-09T00:00:00+00:00",
    "sources": [
      {
        "id": "82cf1e5ed5d6b74255ea7c2d29340b4b",
        "name": "21st Century Business Herald ",
        "url": "https://www.21jingji.com",
        "country": "cn"
      }
    ],
    "original_forms": [
      "华特气体"
    ]
  },
  "国星光电": {
    "first_seen": "2025-12-09T00:00:00+00:00",
    "sources": [
      {
        "id": "82cf1e5ed5d6b74255ea7c2d29340b4b",
        "name": "21st Century Business Herald ",
        "url": "https://www.21jingji.com",
        "country": "cn"
      }
    ],
    "original_forms": [
      "国星光电"
    ]
  },
  "联动科技": {
    "first_seen": "2025-12-09T00:00:00+00:00",
    "sources": [],
    "original_forms": [
      "蓝箭电子",
      "联动科技"
    ]
  },
  "希荻微": {
    "first_seen": "2025-12-09T00:00:00+00:00",
    "sources": [
      {
        "id": "82cf1e5ed5d6b74255ea7c2d29340b4b",
        "name": "21st Century Business Herald ",
        "url": "https://www.21jingji.com",
        "country": "cn"
      }
    ],
    "original_forms": [
      "希荻微"
    ]
  },
  "佛山": {
    "first_seen": "2025-12-09T00:00:00+00:00",
    "sources": [
      {
        "id": "82cf1e5ed5d6b74255ea7c2d29340b4b",
        "name": "21st Century Business Herald ",
        "url": "https://www.21jingji.com",
        "country": "cn"
      }
    ],
    "original_forms": [
      "佛山"
    ]
  },
  "微信": {
    "first_seen": "2025-12-07T03:00:00+00:00",
    "sources": [
      {
        "id": "ec8a18e873d0452c6b532d7a46d9671e",
        "name": "Sankei Shimbun",
        "url": "https://www.sankei.com",
        "country": "jp"
      }
    ],
    "original_forms": [
      "微信"
    ]
  },
  "自民党": {
    "first_seen": "2025-12-07T03:00:00+00:00",
    "sources": [
      {
        "id": "ec8a18e873d0452c6b532d7a46d9671e",
        "name": "Sankei Shimbun",
        "url": "https://www.sankei.com",
        "country": "jp"
      }
    ],
    "original_forms": [
      "自民党"
    ]
  },
  "环球时报": {
    "first_seen": "2025-12-07T03:00:00+00:00",
    "sources": [
      {
        "id": "ec8a18e873d0452c6b532d7a46d9671e",
        "name": "Sankei Shimbun",
        "url": "https://www.sankei.com",
        "country": "jp"
      }
    ],
    "original_forms": [
      "環球時報"
    ]
  },
  "中国国际问题研究院": {
    "first_seen": "2025-12-07T03:00:00+00:00",
    "sources": [
      {
        "id": "ec8a18e873d0452c6b532d7a46d9671e",
        "name": "Sankei Shimbun",
        "url": "https://www.sankei.com",
        "country": "jp"
      }
    ],
    "original_forms": [
      "中国国際問題研究院"
    ]
  },
  "日本勢": {
    "first_seen": "2025-12-05T23:00:00+00:00",
    "sources": [
      {
        "id": "f639ca597f9ccec2cc9817cfb31c1ab6",
        "name": "Nihon Keizai Shimbun",
        "url": "https://www.nikkei.com",
        "country": "jp"
      }
    ],
    "original_forms": [
      "日本勢"
    ]
  },
  "経済産業省": {
    "first_seen": "2025-12-05T23:00:00+00:00",
    "sources": [],
    "original_forms": [
      "经济产业省",
      "経済産業省",
      "日本经济产业省",
      "経産省"
    ]
  },
  "ラピダス": {
    "first_seen": "2025-12-05T23:00:00+00:00",
    "sources": [
      {
        "id": "f639ca597f9ccec2cc9817cfb31c1ab6",
        "name": "Nihon Keizai Shimbun",
        "url": "https://www.nikkei.com",
        "country": "jp"
      }
    ],
    "original_forms": [
      "ラピダス"
    ]
  },
  "ispace": {
    "first_seen": "2025-12-05T23:00:00+00:00",
    "sources": [
      {
        "id": "f639ca597f9ccec2cc9817cfb31c1ab6",
        "name": "Nihon Keizai Shimbun",
        "url": "https://www.nikkei.com",
        "country": "jp"
      }
    ],
    "original_forms": [
      "ispace"
    ]
  },
  "美国国会众议院": {
    "first_seen": "2025-12-05T20:21:19+00:00",
    "sources": [
      {
        "id": "d126b04a3817be12a5dd6ea9039393d8",
        "name": "美国之音中文网 (VOA)",
        "url": "https://www.voachinese.com",
        "country": "cn"
      }
    ],
    "original_forms": [
      "U.S. House of Representatives"
    ]
  },
  "中小学": {
    "first_seen": "2025-12-05T20:21:19+00:00",
    "sources": [
      {
        "id": "d126b04a3817be12a5dd6ea9039393d8",
        "name": "美国之音中文网 (VOA)",
        "url": "https://www.voachinese.com",
        "country": "cn"
      }
    ],
    "original_forms": [
      "K-12 schools"
    ]
  },
  "汤姆·基恩": {
    "first_seen": "2025-12-04T15:57:03+00:00",
    "sources": [
      {
        "id": "d126b04a3817be12a5dd6ea9039393d8",
        "name": "美国之音中文网 (VOA)",
        "url": "https://www.voachinese.com",
        "country": "cn"
      }
    ],
    "original_forms": [
      "Tom Kean",
      "汤姆·基恩"
    ]
  },
  "朱莉·约翰逊": {
    "first_seen": "2025-12-04T15:57:03+00:00",
    "sources": [
      {
        "id": "d126b04a3817be12a5dd6ea9039393d8",
        "name": "美国之音中文网 (VOA)",
        "url": "https://www.voachinese.com",
        "country": "cn"
      }
    ],
    "original_forms": [
      "Julie Johnson",
      "朱莉·约翰逊"
    ]
  },
  "美国商务部产业与安全局": {
    "first_seen": "2025-12-04T15:57:03+00:00",
    "sources": [
      {
        "id": "d126b04a3817be12a5dd6ea9039393d8",
        "name": "美国之音中文网 (VOA)",
        "url": "https://www.voachinese.com",
        "country": "cn"
      }
    ],
    "original_forms": [
      "BIS",
      "美国商务部产业与安全局(BIS)"
    ]
  },
  "福特汽车销售服务有限公司": {
    "first_seen": "2025-12-05T00:00:00+00:00",
    "sources": [
      {
        "id": "82cf1e5ed5d6b74255ea7c2d29340b4b",
        "name": "21st Century Business Herald ",
        "url": "https://www.21jingji.com",
        "country": "cn"
      }
    ],
    "original_forms": [
      "福特汽车销售服务有限公司"
    ]
  },
  "福特": {
    "first_seen": "2025-12-05T00:00:00+00:00",
    "sources": [
      {
        "id": "82cf1e5ed5d6b74255ea7c2d29340b4b",
        "name": "21st Century Business Herald ",
        "url": "https://www.21jingji.com",
        "country": "cn"
      }
    ],
    "original_forms": [
      "福特"
    ]
  },
  "江铃福特": {
    "first_seen": "2025-12-05T00:00:00+00:00",
    "sources": [
      {
        "id": "82cf1e5ed5d6b74255ea7c2d29340b4b",
        "name": "21st Century Business Herald ",
        "url": "https://www.21jingji.com",
        "country": "cn"
      }
    ],
    "original_forms": [
      "江铃福特"
    ]
  },
  "福特纵横": {
    "first_seen": "2025-12-05T00:00:00+00:00",
    "sources": [
      {
        "id": "82cf1e5ed5d6b74255ea7c2d29340b4b",
        "name": "21st Century Business Herald ",
        "url": "https://www.21jingji.com",
        "country": "cn"
      }
    ],
    "original_forms": [
      "福特纵横"
    ]
  },
  "蒙迪欧": {
    "first_seen": "2025-12-05T00:00:00+00:00",
    "sources": [
      {
        "id": "82cf1e5ed5d6b74255ea7c2d29340b4b",
        "name": "21st Century Business Herald ",
        "url": "https://www.21jingji.com",
        "country": "cn"
      }
    ],
    "original_forms": [
      "蒙迪欧"
    ]
  },
  "锐界": {
    "first_seen": "2025-12-05T00:00:00+00:00",
    "sources": [],
    "original_forms": [
      "长安福特",
      "锐界"
    ]
  },
  "F-150猛禽": {
    "first_seen": "2025-12-05T00:00:00+00:00",
    "sources": [
      {
        "id": "82cf1e5ed5d6b74255ea7c2d29340b4b",
        "name": "21st Century Business Herald ",
        "url": "https://www.21jingji.com",
        "country": "cn"
      }
    ],
    "original_forms": [
      "F-150猛禽"
    ]
  },
  "游骑侠Ranger": {
    "first_seen": "2025-12-05T00:00:00+00:00",
    "sources": [
      {
        "id": "82cf1e5ed5d6b74255ea7c2d29340b4b",
        "name": "21st Century Business Herald ",
        "url": "https://www.21jingji.com",
        "country": "cn"
      }
    ],
    "original_forms": [
      "游骑侠Ranger"
    ]
  },
  "国际乒乓球联合会": {
    "first_seen": "2025-12-05T12:54:00+00:00",
    "sources": [
      {
        "id": "02b7b14861d5da81f7deeaa31b363b39",
        "name": "スポニチアネックス Sponichi Annex",
        "url": "https://www.sponichi.co.jp",
        "country": "jp"
      }
    ],
    "original_forms": [
      "ITTF"
    ]
  },
  "成都": {
    "first_seen": "2025-12-05T12:54:00+00:00",
    "sources": [
      {
        "id": "02b7b14861d5da81f7deeaa31b363b39",
        "name": "スポニチアネックス Sponichi Annex",
        "url": "https://www.sponichi.co.jp",
        "country": "jp"
      }
    ],
    "original_forms": [
      "成都",
      "中国・成都"
    ]
  },
  "井村屋集团": {
    "first_seen": "2025-12-05T12:54:00+00:00",
    "sources": [
      {
        "id": "02b7b14861d5da81f7deeaa31b363b39",
        "name": "スポニチアネックス Sponichi Annex",
        "url": "https://www.sponichi.co.jp",
        "country": "jp"
      }
    ],
    "original_forms": [
      "井村屋グループ"
    ]
  },
  "木下集团": {
    "first_seen": "2025-12-05T12:54:00+00:00",
    "sources": [
      {
        "id": "02b7b14861d5da81f7deeaa31b363b39",
        "name": "スポニチアネックス Sponichi Annex",
        "url": "https://www.sponichi.co.jp",
        "country": "jp"
      }
    ],
    "original_forms": [
      "木下グループ"
    ]
  },
  "朝倉未来": {
    "first_seen": "2025-12-04T03:54:57+00:00",
    "sources": [],
    "original_forms": [
      "朝仓未来",
      "朝倉未来"
    ]
  },
  "BreakingDown18": {
    "first_seen": "2025-12-04T03:54:57+00:00",
    "sources": [
      {
        "id": "8c8c20cf5bc864f9ffe0dce373f12abc",
        "name": "Iza",
        "url": "https://www.iza.ne.jp",
        "country": "jp"
      }
    ],
    "original_forms": [
      "BreakingDown18（ブレイキングダウン）",
      "BreakingDown18"
    ]
  },
  "美国国会众议院科学、太空与技术委员会航空航天小组委员会": {
    "first_seen": "2025-12-05T21:37:33+00:00",
    "sources": [
      {
        "id": "d126b04a3817be12a5dd6ea9039393d8",
        "name": "美国之音中文网 (VOA)",
        "url": "https://www.voachinese.com",
        "country": "cn"
      }
    ],
    "original_forms": [
      "House Subcommittee on Space of the House Committee on Science, Space, and Technology"
    ]
  },
  "Rapidus": {
    "first_seen": "2025-12-05T23:00:00+00:00",
    "sources": [
      {
        "id": "f639ca597f9ccec2cc9817cfb31c1ab6",
        "name": "Nihon Keizai Shimbun",
        "url": "https://www.nikkei.com",
        "country": "jp"
      }
    ],
    "original_forms": [
      "ラピダス"
    ]
  },
  "三星": {
    "first_seen": "2025-12-05T23:00:00+00:00",
    "sources": [],
    "original_forms": [
      "サムスン",
      "三星"
    ]
  },
  "MOR": {
    "first_seen": "2025-12-05T23:00:00+00:00",
    "sources": [
      {
        "id": "f639ca597f9ccec2cc9817cfb31c1ab6",
        "name": "Nihon Keizai Shimbun",
        "url": "https://www.nikkei.com",
        "country": "jp"
      }
    ],
    "original_forms": [
      "MOR"
    ]
  },
  "中华人民共和国商务部": {
    "first_seen": "2025-12-04T00:00:00+00:00",
    "sources": [
      {
        "id": "82cf1e5ed5d6b74255ea7c2d29340b4b",
        "name": "21st Century Business Herald ",
        "url": "https://www.21jingji.com",
        "country": "cn"
      }
    ],
    "original_forms": [
      "商务部"
    ]
  },
  "中华人民共和国财政部": {
    "first_seen": "2025-12-04T00:00:00+00:00",
    "sources": [
      {
        "id": "82cf1e5ed5d6b74255ea7c2d29340b4b",
        "name": "21st Century Business Herald ",
        "url": "https://www.21jingji.com",
        "country": "cn"
      }
    ],
    "original_forms": [
      "财政部"
    ]
  },
  "上海": {
    "first_seen": "2025-12-04T00:00:00+00:00",
    "sources": [
      {
        "id": "82cf1e5ed5d6b74255ea7c2d29340b4b",
        "name": "21st Century Business Herald ",
        "url": "https://www.21jingji.com",
        "country": "cn"
      }
    ],
    "original_forms": [
      "上海"
    ]
  },
  "广州": {
    "first_seen": "2025-12-04T00:00:00+00:00",
    "sources": [
      {
        "id": "82cf1e5ed5d6b74255ea7c2d29340b4b",
        "name": "21st Century Business Herald ",
        "url": "https://www.21jingji.com",
        "country": "cn"
      }
    ],
    "original_forms": [
      "广州"
    ]
  },
  "天津": {
    "first_seen": "2025-12-04T00:00:00+00:00",
    "sources": [
      {
        "id": "82cf1e5ed5d6b74255ea7c2d29340b4b",
        "name": "21st Century Business Herald ",
        "url": "https://www.21jingji.com",
        "country": "cn"
      }
    ],
    "original_forms": [
      "天津"
    ]
  },
  "重庆": {
    "first_seen": "2025-12-04T00:00:00+00:00",
    "sources": [
      {
        "id": "82cf1e5ed5d6b74255ea7c2d29340b4b",
        "name": "21st Century Business Herald ",
        "url": "https://www.21jingji.com",
        "country": "cn"
      }
    ],
    "original_forms": [
      "重庆"
    ]
  },
  "CLOSE YOUR EYES": {
    "first_seen": "2025-12-04T01:31:11+00:00",
    "sources": [
      {
        "id": "ec8a18e873d0452c6b532d7a46d9671e",
        "name": "Sankei Shimbun",
        "url": "https://www.sankei.com",
        "country": "jp"
      }
    ],
    "original_forms": [
      "CLOSE YOUR EYES"
    ]
  },
  "ケンシン": {
    "first_seen": "2025-12-04T01:31:11+00:00",
    "sources": [],
    "original_forms": [
      "KENSHIN",
      "ケンシン"
    ]
  },
  "aespa": {
    "first_seen": "2025-12-04T05:35:50+00:00",
    "sources": [
      {
        "id": "d7af3aa0ba98393ebfc367c4b509375e",
        "name": "Yukan Fuji",
        "url": "https://www.zakzak.co.jp",
        "country": "jp"
      }
    ],
    "original_forms": [
      "aespa"
    ]
  },
  "宁宁": {
    "first_seen": "2025-12-04T05:35:50+00:00",
    "sources": [],
    "original_forms": [
      "NINGNING",
      "宁宁",
      "ニンニン"
    ]
  },
  "NHK": {
    "first_seen": "2025-12-04T05:35:50+00:00",
    "sources": [
      {
        "id": "d7af3aa0ba98393ebfc367c4b509375e",
        "name": "Yukan Fuji",
        "url": "https://www.zakzak.co.jp",
        "country": "jp"
      }
    ],
    "original_forms": [
      "NHK"
    ]
  },
  "广岛": {
    "first_seen": "2025-12-04T05:35:50+00:00",
    "sources": [
      {
        "id": "d7af3aa0ba98393ebfc367c4b509375e",
        "name": "Yukan Fuji",
        "url": "https://www.zakzak.co.jp",
        "country": "jp"
      }
    ],
    "original_forms": [
      "広島"
    ]
  },
  "原爆": {
    "first_seen": "2025-12-04T05:35:50+00:00",
    "sources": [
      {
        "id": "d7af3aa0ba98393ebfc367c4b509375e",
        "name": "Yukan Fuji",
        "url": "https://www.zakzak.co.jp",
        "country": "jp"
      }
    ],
    "original_forms": [
      "原爆"
    ]
  },
  "产经新闻": {
    "first_seen": "2025-12-04T05:35:50+00:00",
    "sources": [
      {
        "id": "d7af3aa0ba98393ebfc367c4b509375e",
        "name": "Yukan Fuji",
        "url": "https://www.zakzak.co.jp",
        "country": "jp"
      }
    ],
    "original_forms": [
      "産経ニュース"
    ]
  },
  "蘑菇云灯": {
    "first_seen": "2025-12-04T05:35:50+00:00",
    "sources": [
      {
        "id": "d7af3aa0ba98393ebfc367c4b509375e",
        "name": "Yukan Fuji",
        "url": "https://www.zakzak.co.jp",
        "country": "jp"
      }
    ],
    "original_forms": [
      "きのこ雲ランプ"
    ]
  },
  "瑞典": {
    "first_seen": "2025-12-04T12:50:00+00:00",
    "sources": [
      {
        "id": "02b7b14861d5da81f7deeaa31b363b39",
        "name": "スポニチアネックス Sponichi Annex",
        "url": "https://www.sponichi.co.jp",
        "country": "jp"
      }
    ],
    "original_forms": [
      "スウェーデン"
    ]
  },
  "户上隼辅": {
    "first_seen": "2025-12-04T12:50:00+00:00",
    "sources": [
      {
        "id": "02b7b14861d5da81f7deeaa31b363b39",
        "name": "スポニチアネックス Sponichi Annex",
        "url": "https://www.sponichi.co.jp",
        "country": "jp"
      }
    ],
    "original_forms": [
      "戸上隼輔"
    ]
  },
  "早田雏": {
    "first_seen": "2025-12-04T12:50:00+00:00",
    "sources": [],
    "original_forms": [
      "早田雏",
      "早田ひな"
    ]
  },
  "日本生命": {
    "first_seen": "2025-12-04T12:50:00+00:00",
    "sources": [],
    "original_forms": [
      "日本生命保险相互会社",
      "日本生命保险公司",
      "日本生命"
    ]
  },
  "伊藤美诚": {
    "first_seen": "2025-12-04T12:50:00+00:00",
    "sources": [
      {
        "id": "02b7b14861d5da81f7deeaa31b363b39",
        "name": "スポニチアネックス Sponichi Annex",
        "url": "https://www.sponichi.co.jp",
        "country": "jp"
      }
    ],
    "original_forms": [
      "伊藤美誠"
    ]
  },
  "スターツ": {
    "first_seen": "2025-12-04T12:50:00+00:00",
    "sources": [
      {
        "id": "02b7b14861d5da81f7deeaa31b363b39",
        "name": "スポニチアネックス Sponichi Annex",
        "url": "https://www.sponichi.co.jp",
        "country": "jp"
      }
    ],
    "original_forms": [
      "スターツ"
    ]
  },
  "株式会社oricon ME": {
    "first_seen": "2025-12-04T03:01:13+00:00",
    "sources": [
      {
        "id": "ec8a18e873d0452c6b532d7a46d9671e",
        "name": "Sankei Shimbun",
        "url": "https://www.sankei.com",
        "country": "jp"
      }
    ],
    "original_forms": [
      "株式会社oricon ME"
    ]
  },
  "宇部進学教室": {
    "first_seen": "2025-12-04T03:01:13+00:00",
    "sources": [
      {
        "id": "ec8a18e873d0452c6b532d7a46d9671e",
        "name": "Sankei Shimbun",
        "url": "https://www.sankei.com",
        "country": "jp"
      }
    ],
    "original_forms": [
      "宇部進学教室"
    ]
  },
  "個別指導塾サクラサクセス": {
    "first_seen": "2025-12-04T03:01:13+00:00",
    "sources": [
      {
        "id": "ec8a18e873d0452c6b532d7a46d9671e",
        "name": "Sankei Shimbun",
        "url": "https://www.sankei.com",
        "country": "jp"
      }
    ],
    "original_forms": [
      "個別指導塾サクラサクセス"
    ]
  },
  "霍飞明": {
    "first_seen": "2025-12-04T00:00:00+00:00",
    "sources": [],
    "original_forms": [
      "霍飞明博士",
      "霍飞明",
      "中国德国商会"
    ]
  },
  "南方财经": {
    "first_seen": "2025-12-04T00:00:00+00:00",
    "sources": [
      {
        "id": "82cf1e5ed5d6b74255ea7c2d29340b4b",
        "name": "21st Century Business Herald ",
        "url": "https://www.21jingji.com",
        "country": "cn"
      }
    ],
    "original_forms": [
      "南方财经"
    ]
  },
  "21世纪经济报道": {
    "first_seen": "2025-12-04T00:00:00+00:00",
    "sources": [],
    "original_forms": [
      "21世纪经济报道",
      "南方财经21世纪经济报道"
    ]
  },
  "埃马纽埃尔·马克龙": {
    "first_seen": "2025-12-04T00:00:00+00:00",
    "sources": [
      {
        "id": "82cf1e5ed5d6b74255ea7c2d29340b4b",
        "name": "21st Century Business Herald ",
        "url": "https://www.21jingji.com",
        "country": "cn"
      }
    ],
    "original_forms": [
      "马克龙"
    ]
  },
  "对外经济贸易大学": {
    "first_seen": "2025-12-04T00:00:00+00:00",
    "sources": [],
    "original_forms": [
      "对外经济贸易大学",
      "对外经济贸易大学法国经济研究中心"
    ]
  },
  "赵永升": {
    "first_seen": "2025-12-04T00:00:00+00:00",
    "sources": [
      {
        "id": "82cf1e5ed5d6b74255ea7c2d29340b4b",
        "name": "21st Century Business Herald ",
        "url": "https://www.21jingji.com",
        "country": "cn"
      }
    ],
    "original_forms": [
      "赵永升"
    ]
  },
  "美国参议员": {
    "first_seen": "2025-12-03T20:00:35+00:00",
    "sources": [
      {
        "id": "d126b04a3817be12a5dd6ea9039393d8",
        "name": "美国之音中文网 (VOA)",
        "url": "https://www.voachinese.com",
        "country": "cn"
      }
    ],
    "original_forms": [
      "U.S. senators"
    ]
  },
  "美国国会参议院外交关系委员会东亚、太平洋与国际网络安全政策小组委员会": {
    "first_seen": "2025-12-03T20:00:35+00:00",
    "sources": [
      {
        "id": "d126b04a3817be12a5dd6ea9039393d8",
        "name": "美国之音中文网 (VOA)",
        "url": "https://www.voachinese.com",
        "country": "cn"
      }
    ],
    "original_forms": [
      "Senate Foreign Relations Committee's Subcommittee on East Asia, the Pacific, and International Cybersecurity Policy",
      "美国国会参议院外交关系委员会东亚、太平洋与国际网络安全政策小组委员会"
    ]
  },
  "皮特·里基茨": {
    "first_seen": "2025-12-03T20:00:35+00:00",
    "sources": [
      {
        "id": "d126b04a3817be12a5dd6ea9039393d8",
        "name": "美国之音中文网 (VOA)",
        "url": "https://www.voachinese.com",
        "country": "cn"
      }
    ],
    "original_forms": [
      "Pete Ricketts"
    ]
  },
  "深圳证券交易所": {
    "first_seen": "2025-12-04T00:00:00+00:00",
    "sources": [
      {
        "id": "82cf1e5ed5d6b74255ea7c2d29340b4b",
        "name": "21st Century Business Herald ",
        "url": "https://www.21jingji.com",
        "country": "cn"
      }
    ],
    "original_forms": [
      "深交所"
    ]
  },
  "法兰克福": {
    "first_seen": "2025-12-04T00:00:00+00:00",
    "sources": [
      {
        "id": "82cf1e5ed5d6b74255ea7c2d29340b4b",
        "name": "21st Century Business Herald ",
        "url": "https://www.21jingji.com",
        "country": "cn"
      }
    ],
    "original_forms": [
      "法兰克福"
    ]
  },
  "中华人民共和国国家卫生健康委员会": {
    "first_seen": "2025-12-03T00:00:00+00:00",
    "sources": [
      {
        "id": "82cf1e5ed5d6b74255ea7c2d29340b4b",
        "name": "21st Century Business Herald ",
        "url": "https://www.21jingji.com",
        "country": "cn"
      }
    ],
    "original_forms": [
      "国家卫生健康委"
    ]
  },
  "郭燕红": {
    "first_seen": "2025-12-03T00:00:00+00:00",
    "sources": [
      {
        "id": "82cf1e5ed5d6b74255ea7c2d29340b4b",
        "name": "21st Century Business Herald ",
        "url": "https://www.21jingji.com",
        "country": "cn"
      }
    ],
    "original_forms": [
      "郭燕红"
    ]
  },
  "约翰·马丁尼斯": {
    "first_seen": "2025-12-03T16:39:50+00:00",
    "sources": [],
    "original_forms": [
      "约翰·马蒂尼斯",
      "ジョン・マルティニス",
      "约翰·马丁尼斯"
    ]
  },
  "特拉维夫": {
    "first_seen": "2025-12-03T16:39:50+00:00",
    "sources": [
      {
        "id": "3988c993805f56d9bc898af220571e83",
        "name": "ブルームバーグ",
        "url": "https://www.bloomberg.co.jp",
        "country": "jp"
      }
    ],
    "original_forms": [
      "テルアビブ"
    ]
  },
  "彭博新闻社": {
    "first_seen": "2025-12-03T16:39:50+00:00",
    "sources": [
      {
        "id": "3988c993805f56d9bc898af220571e83",
        "name": "ブルームバーグ",
        "url": "https://www.bloomberg.co.jp",
        "country": "jp"
      }
    ],
    "original_forms": [
      "ブルームバーグニュース"
    ]
  },
  "大韩民国": {
    "first_seen": "2025-12-05T12:54:00+00:00",
    "sources": [
      {
        "id": "02b7b14861d5da81f7deeaa31b363b39",
        "name": "スポニチアネックス Sponichi Annex",
        "url": "https://www.sponichi.co.jp",
        "country": "jp"
      }
    ],
    "original_forms": [
      "韓国"
    ]
  },
  "松岛辉空": {
    "first_seen": "2025-12-05T12:54:00+00:00",
    "sources": [
      {
        "id": "02b7b14861d5da81f7deeaa31b363b39",
        "name": "スポニチアネックス Sponichi Annex",
        "url": "https://www.sponichi.co.jp",
        "country": "jp"
      }
    ],
    "original_forms": [
      "松島輝空"
    ]
  },
  "张本美和": {
    "first_seen": "2025-12-05T12:54:00+00:00",
    "sources": [
      {
        "id": "02b7b14861d5da81f7deeaa31b363b39",
        "name": "スポニチアネックス Sponichi Annex",
        "url": "https://www.sponichi.co.jp",
        "country": "jp"
      }
    ],
    "original_forms": [
      "張本美和"
    ]
  },
  "美国中小学": {
    "first_seen": "2025-12-05T20:21:19+00:00",
    "sources": [
      {
        "id": "d126b04a3817be12a5dd6ea9039393d8",
        "name": "美国之音中文网 (VOA)",
        "url": "https://www.voachinese.com",
        "country": "cn"
      }
    ],
    "original_forms": [
      "American elementary and secondary schools"
    ]
  },
  "民主党": {
    "first_seen": "2025-12-04T15:57:03+00:00",
    "sources": [
      {
        "id": "d126b04a3817be12a5dd6ea9039393d8",
        "name": "美国之音中文网 (VOA)",
        "url": "https://www.voachinese.com",
        "country": "cn"
      }
    ],
    "original_forms": [
      "民主"
    ]
  },
  "美国众议院": {
    "first_seen": "2025-12-04T15:57:03+00:00",
    "sources": [],
    "original_forms": [
      "美国众议员",
      "美国众议院",
      "Congress",
      "美国国会"
    ]
  },
  "福特汽车公司": {
    "first_seen": "2025-12-05T00:00:00+00:00",
    "sources": [
      {
        "id": "82cf1e5ed5d6b74255ea7c2d29340b4b",
        "name": "21st Century Business Herald ",
        "url": "https://www.21jingji.com",
        "country": "cn"
      }
    ],
    "original_forms": [
      "福特"
    ]
  },
  "福特中国": {
    "first_seen": "2025-12-05T00:00:00+00:00",
    "sources": [
      {
        "id": "82cf1e5ed5d6b74255ea7c2d29340b4b",
        "name": "21st Century Business Herald ",
        "url": "https://www.21jingji.com",
        "country": "cn"
      }
    ],
    "original_forms": [
      "福特中国"
    ]
  },
  "陈晓波": {
    "first_seen": "2025-12-05T00:00:00+00:00",
    "sources": [
      {
        "id": "82cf1e5ed5d6b74255ea7c2d29340b4b",
        "name": "21st Century Business Herald ",
        "url": "https://www.21jingji.com",
        "country": "cn"
      }
    ],
    "original_forms": [
      "陈晓波"
    ]
  },
  "埼玉超级竞技场": {
    "first_seen": "2025-12-04T03:54:57+00:00",
    "sources": [],
    "original_forms": [
      "埼玉超级竞技场",
      "さいたまスーパーアリーナ"
    ]
  },
  "社区竞技场": {
    "first_seen": "2025-12-04T03:54:57+00:00",
    "sources": [
      {
        "id": "8c8c20cf5bc864f9ffe0dce373f12abc",
        "name": "Iza",
        "url": "https://www.iza.ne.jp",
        "country": "jp"
      }
    ],
    "original_forms": [
      "コミュニティアリーナ"
    ]
  },
  "岛根县松江市": {
    "first_seen": "2025-12-04T03:01:13+00:00",
    "sources": [
      {
        "id": "ec8a18e873d0452c6b532d7a46d9671e",
        "name": "Sankei Shimbun",
        "url": "https://www.sankei.com",
        "country": "jp"
      }
    ],
    "original_forms": [
      "島根県松江市"
    ]
  },
  "马克龙": {
    "first_seen": "2025-12-04T00:00:00+00:00",
    "sources": [
      {
        "id": "82cf1e5ed5d6b74255ea7c2d29340b4b",
        "name": "21st Century Business Herald ",
        "url": "https://www.21jingji.com",
        "country": "cn"
      }
    ],
    "original_forms": [
      "马克龙"
    ]
  },
  "Martin Hofmann": {
    "first_seen": "2025-12-04T00:00:00+00:00",
    "sources": [
      {
        "id": "82cf1e5ed5d6b74255ea7c2d29340b4b",
        "name": "21st Century Business Herald ",
        "url": "https://www.21jingji.com",
        "country": "cn"
      }
    ],
    "original_forms": [
      "Martin Hofmann"
    ]
  },
  "中国健康教育与健康促进大会": {
    "first_seen": "2025-12-03T00:00:00+00:00",
    "sources": [
      {
        "id": "82cf1e5ed5d6b74255ea7c2d29340b4b",
        "name": "21st Century Business Herald ",
        "url": "https://www.21jingji.com",
        "country": "cn"
      }
    ],
    "original_forms": [
      "第十八届中国健康教育与健康促进大会"
    ]
  },
  "国家卫生健康委": {
    "first_seen": "2025-12-03T00:00:00+00:00",
    "sources": [
      {
        "id": "82cf1e5ed5d6b74255ea7c2d29340b4b",
        "name": "21st Century Business Herald ",
        "url": "https://www.21jingji.com",
        "country": "cn"
      }
    ],
    "original_forms": [
      "国家卫生健康委"
    ]
  }
}